fleet_rec-0.0.3.dist-info/DESCRIPTION.rst
fleet_rec-0.0.3.dist-info/METADATA
fleet_rec-0.0.3.dist-info/RECORD
fleet_rec-0.0.3.dist-info/WHEEL
fleet_rec-0.0.3.dist-info/metadata.json
fleet_rec-0.0.3.dist-info/top_level.txt
fleetrec/__init__.py
fleetrec/check.py
fleetrec/run.py
fleetrec/core/__init__.py
fleetrec/core/factory.py
fleetrec/core/layer.py
fleetrec/core/metric.py
fleetrec/core/model.py
fleetrec/core/reader.py
fleetrec/core/trainer.py
fleetrec/core/engine/__init__.py
fleetrec/core/engine/engine.py
fleetrec/core/engine/local_cluster_engine.py
fleetrec/core/engine/local_mpi_engine.py
fleetrec/core/metrics/__init__.py
fleetrec/core/metrics/auc_metrics.py
fleetrec/core/modules/__init__.py
fleetrec/core/modules/coding/__init__.py
fleetrec/core/modules/coding/layers.py
fleetrec/core/modules/modul/__init__.py
fleetrec/core/modules/modul/build.py
fleetrec/core/modules/modul/layers.py
fleetrec/core/trainers/__init__.py
fleetrec/core/trainers/cluster_trainer.py
fleetrec/core/trainers/ctr_coding_trainer.py
fleetrec/core/trainers/ctr_modul_trainer.py
fleetrec/core/trainers/single_trainer.py
fleetrec/core/trainers/transpiler_trainer.py
fleetrec/core/utils/__init__.py
fleetrec/core/utils/dataloader_instance.py
fleetrec/core/utils/dataset.py
fleetrec/core/utils/dataset_instance.py
fleetrec/core/utils/envs.py
fleetrec/core/utils/fs.py
fleetrec/core/utils/table.py
fleetrec/core/utils/util.py
fleetrec/demo/__init__.py
fleetrec/demo/user_define_trainer.py
fleetrec/doc/__init__.py
fleetrec/models/__init__.py
fleetrec/models/rank/__init__.py
fleetrec/models/rank/criteo_reader.py
fleetrec/models/rank/dnn/__init__.py
fleetrec/models/rank/dnn/model.py
fleetrec/models/rank/dnn/data/test/sample_test.txt
fleetrec/models/rank/dnn/data/train/sample_train.txt
fleetrec/tests/__init__.py
fleetrec/tools/__init__.py
