Metadata-Version: 2.0
Name: fleet-rec
Version: 0.0.3
Summary: fleet-rec
Home-page: https://github.com/seiriosPlus/FleetRec
Author: seiriosPlus
Author-email: tangwei12@baidu.com
License: UNKNOWN
Platform: UNKNOWN
Requires-Python: >=2.7
Requires-Dist: paddlepaddle (==1.7.2)
Requires-Dist: pyyaml (>=5.1.1)
